kissml/__init__.py
kissml/core.py
kissml/disk.py
kissml/serializers.py
kissml/settings.py
kissml/step.py
kissml/types.py
kissml-0.2.0.dist-info/licenses/LICENSE
kissml-0.2.0.dist-info/METADATA
kissml-0.2.0.dist-info/WHEEL
kissml-0.2.0.dist-info/top_level.txt
kissml-0.2.0.dist-info/RECORD
