Metadata-Version: 2.4
Name: kissml
Version: 0.2.0
Summary: Keep It Simple Stupid Tools for Machine Learning
Author-email: Lou Kratz <kissml@lou.dev>
License-Expression: CC-BY-NC-ND-4.0
Project-URL: Homepage, https://github.com/lou-k/kissml
Requires-Python: >=3.12
License-File: LICENSE
Requires-Dist: diskcache>=5.6.3
Requires-Dist: pandas>=2.3.3
Requires-Dist: pydantic>=2.12.5
Requires-Dist: pydantic-settings>=2.0.0
Dynamic: license-file
